[
  {
    "id": "{DEMO_CATEGORY_0}",
    "parentId": "{NAVIGATION_CATEGORY_ID}",
    "cmsPageId": "{CMS_PAGE_ID}",
    "mediaId": "pexels-photo-1565982",
    "active": true,
    "name": "Speisekarte"
  },
  {
    "id": "{DEMO_CATEGORY_1}",
    "parentId": "{DEMO_CATEGORY_0}",
    "mediaId": "category\/rum",
    "active": true,
    "name": "Cocktail mit Rum"
  },
  {
    "id": "{DEMO_CATEGORY_2}",
    "parentId": "{DEMO_CATEGORY_0}",
    "mediaId": "category\/gin",
    "active": true,
    "name": "Cocktail mit Gin"
  },
  {
    "id": "{DEMO_CATEGORY_3}",
    "parentId": "{DEMO_CATEGORY_0}",
    "mediaId": "category\/vodka",
    "active": true,
    "name": "Cocktail mit Wodka"
  },
  {
    "id": "{DEMO_CATEGORY_4}",
    "parentId": "{DEMO_CATEGORY_0}",
    "mediaId": "category\/sahne",
    "active": true,
    "name": "Cocktail mit Sahne"
  },
  {
    "id": "{DEMO_CATEGORY_5}",
    "parentId": "{DEMO_CATEGORY_0}",
    "mediaId": "category\/ohnealkohol",
    "active": true,
    "name": "Cocktails ohne Alkohol"
  },
  {
    "id": "{DEMO_CATEGORY_6}",
    "parentId": "{DEMO_CATEGORY_0}",
    "mediaId": "category\/flaschen",
    "active": true,
    "name": "Hochprozentiges in Flaschen"
  },
  {
    "id": "{DEMO_CATEGORY_7}",
    "parentId": "{DEMO_CATEGORY_0}",
    "mediaId": "category\/juice",
    "active": true,
    "name": "Alkoholfreie Getränke"
  },
  {
    "id": "{DEMO_CATEGORY_8}",
    "parentId": "{DEMO_CATEGORY_0}",
    "mediaId": "category\/lime",
    "active": true,
    "name": "Sonstige Zutaten"
  }
]
